examples/__init__.py
ku/__init__.py
ku/utility.py
ku/applications_ext/__init__.py
ku/applications_ext/nobody_convnet2d.py
ku/applications_ext/nobody_convnet3d.py
ku/backend_ext/__init__.py
ku/backend_ext/tensorflow_backend.py
ku/backprop/__init__.py
ku/backprop/autoencoder.py
ku/backprop/gan.py
ku/composite_layer/__init__.py
ku/composite_layer/dense_composite_layer.py
ku/composite_layer/transformer.py
ku/ebm/__init__.py
ku/ebm/dbn.py
ku/ebm/rbm.py
ku/engine_ext/__init__.py
ku/engine_ext/training.py
ku/gnn_layer/__init__.py
ku/gnn_layer/core.py
ku/image_utils/__init__.py
ku/image_utils/utility.py
ku/initializers_ext/__init__.py
ku/initializers_ext/initializers.py
ku/layer_ext/__init__.py
ku/layer_ext/attention.py
ku/layer_ext/convolution.py
ku/layer_ext/core.py
ku/layer_ext/normalization.py
ku/layer_ext/position_encoding.py
ku/layer_ext/style.py
ku/loss_ext/__init__.py
ku/loss_ext/loss.py
ku/metrics_ext/__init__.py
ku/metrics_ext/metrics.py
keras_unsupervised-1.1.3.dev1.dist-info/LICENSE
keras_unsupervised-1.1.3.dev1.dist-info/METADATA
keras_unsupervised-1.1.3.dev1.dist-info/WHEEL
keras_unsupervised-1.1.3.dev1.dist-info/top_level.txt
keras_unsupervised-1.1.3.dev1.dist-info/RECORD
