Metadata-Version: 2.1
Name: keras-unsupervised
Version: 1.1.3.dev1
Summary: Keras based unsupervised learning framework.
Home-page: https://github.com/tonandr/keras_unsupervised
Author: Inwoo Chung
Author-email: gutomitai@gmail.com
License: UNKNOWN
Project-URL: Bug Reports, https://github.com/tonandr/keras_unsupervised/issues
Project-URL: Source, https://github.com/tonandr/keras_unsupervised/
Keywords: keras deepleaning unsupervised semisupervised restricted-botlzmann-machine deep-belief-network autoencoder generative-adversarial-networks
Platform: UNKNOWN
Classifier: Development Status :: 4 - Beta
Classifier: Intended Audience :: Developers
Classifier: Intended Audience :: Science/Research
Classifier: License :: OSI Approved :: BSD License
Classifier: Programming Language :: Python :: 3
Classifier: Programming Language :: Python :: 3.8
Requires-Python: ==3.8
License-File: LICENSE
Requires-Dist: tensorflow-probability (==0.11)
Requires-Dist: pandas
Requires-Dist: scikit-image
Requires-Dist: matplotlib
Requires-Dist: opencv-contrib-python
